{
  "swagger": "2.0",
  "info": {
    "version": "1.0",
    "title": "Gerenciamento de Protestos",
    "contact": {
      "name": "CertDox",
      "email": "contato@certdox.com.br"
    }
  },
  "host": "127.0.0.1:8080",
  "basePath": "/datasnap/rest/TServerMethods1/",
  "schemes": [
    "http"
  ],
  "paths": {
    "/envio_protesto": {
      "post": {         
        "tags":["protesto"],
        "description": "",
        "consumes":["application/json"],
        "produces":["application/json"],
        "parameters": [
          {
            "in":"body",
            "name": "Protestos",      
            "description": "",
            "required": true,
            "type": "array",
            "schema": {
                 "type":"array",
                     "items":{
                    "$ref":"#/definitions/Protesto"}}
          }
        ],
        "responses": {
          "201": {
            "description": "Recebido"
          }
        }
      }
    }
    ,
    "/cancelamento_protesto": {
      "post": {         
        "tags":["protesto"],
        "description": "",
        "consumes":["application/json"],
        "produces":["application/json"],
        "parameters": [
          {
            "in":"body",
            "name": "Protestos",      
            "description": "",
            "required": true,
            "type": "array",
            "schema": {"$ref":"#/definitions/Protesto"}
          }
        ],
        "responses": {
          "201": {
            "description": "Recebido"
          }
        }
      }
    }
    ,
    "/desistencia_protesto": {
      "post": {         
        "tags":["protesto"],
        "description": "",
        "consumes":["application/json"],
        "produces":["application/json"],
        "parameters": [
          {
            "in":"body",
            "name": "Protestos",      
            "description": "",
            "required": true,
            "type": "array",
            "schema": {"$ref":"#/definitions/Protesto"}
          }
        ],
        "responses": {
          "201": {
            "description": "Recebido"
          }
        }
      }
    }
    ,
    "/status_protesto":{
    "get": {     
        "parameters": [
          {
            "in":"query",
            "name": "Identificação do Protesto",      
            "description": "",
            "required": true,
            "type": "string"
          }],
        "responses": {
              "200": {
              "description": "Concluído"
          }
        }
    }
    }
  },
    "definitions":{
        "Protesto":{"$ref":"/protestos_poc/expand/swagger/Protesto.json#Protesto"},
        "Titulo":{"$ref":"/protestos_poc/expand/swagger/Protesto.json#ProtestoTitulo"},
        "Cedente":{"$ref":"/protestos_poc/expand/swagger/ProtestoCedente.json#Cedente"},
        "Devedor":{"$ref":"/protestos_poc/expand/swagger/ProtestoDevedor.json#Devedor"},
        "Sacador":{"$ref":"/protestos_poc/expand/swagger/ProtestoSacador.json#Sacador"}
    }
}